concert/__init__.py
concert/_aimport.py
concert/_ipython_setup.py
concert/base.py
concert/config.py
concert/exthook.py
concert/helpers.py
concert/imageprocessing.py
concert/loghandler.py
concert/measures.py
concert/optimization.py
concert/progressbar.py
concert/quantities.py
concert/readers.py
concert/storage.py
concert/typing.py
concert/writers.py
concert/coroutines/__init__.py
concert/coroutines/base.py
concert/coroutines/filters.py
concert/coroutines/sinks.py
concert/devices/__init__.py
concert/devices/base.py
concert/devices/dummy.py
concert/devices/attenuatorboxes/__init__.py
concert/devices/attenuatorboxes/base.py
concert/devices/attenuatorboxes/dummy.py
concert/devices/cameras/__init__.py
concert/devices/cameras/base.py
concert/devices/cameras/dummy.py
concert/devices/cameras/pco.py
concert/devices/cameras/uca.py
concert/devices/detectors/__init__.py
concert/devices/detectors/base.py
concert/devices/detectors/dummy.py
concert/devices/elementselectors/__init__.py
concert/devices/elementselectors/base.py
concert/devices/grippers/__init__.py
concert/devices/grippers/base.py
concert/devices/grippers/dummy.py
concert/devices/io/__init__.py
concert/devices/io/base.py
concert/devices/io/dummy.py
concert/devices/lenschangers/__init__.py
concert/devices/lenschangers/base.py
concert/devices/lenschangers/dummy.py
concert/devices/lightsources/__init__.py
concert/devices/lightsources/base.py
concert/devices/lightsources/dummy.py
concert/devices/monochromators/__init__.py
concert/devices/monochromators/base.py
concert/devices/monochromators/doublemonochromator.py
concert/devices/monochromators/dummy.py
concert/devices/motors/__init__.py
concert/devices/motors/base.py
concert/devices/motors/dummy.py
concert/devices/photodiodes/__init__.py
concert/devices/photodiodes/base.py
concert/devices/photodiodes/dummy.py
concert/devices/positioners/__init__.py
concert/devices/positioners/base.py
concert/devices/positioners/dummy.py
concert/devices/positioners/imaging.py
concert-0.33.0.dist-info/licenses/LICENSE
concert-0.33.0.dist-info/METADATA
concert-0.33.0.dist-info/WHEEL
concert-0.33.0.dist-info/top_level.txt
concert-0.33.0.dist-info/RECORD
