Metadata-Version: 2.4
Name: concert
Version: 0.33.0
Summary: Lightweight beamline control system
Home-page: http://github.com/ufo-kit/concert
Author: Matthias Vogelgesang
Author-email: matthias.vogelgesang@kit.edu
License: LGPL
Requires-Python: >=3.7
License-File: LICENSE
Requires-Dist: ipython
Requires-Dist: matplotlib
Requires-Dist: numpy
Requires-Dist: pint>=0.12
Requires-Dist: prettytable
Requires-Dist: pyqtgraph
Requires-Dist: pyxdg
Requires-Dist: scipy
Requires-Dist: tifffile
Requires-Dist: pyzmq>=23.2.1
Requires-Dist: psutil
Dynamic: author
Dynamic: author-email
Dynamic: description
Dynamic: home-page
Dynamic: license
Dynamic: license-file
Dynamic: requires-dist
Dynamic: requires-python
Dynamic: summary
